ci_package_tools/__init__.py
ci_package_tools/__main__.py
ci_package_tools/main.py
ci_package_tools-1.0.0.dist-info/METADATA
ci_package_tools-1.0.0.dist-info/WHEEL
ci_package_tools-1.0.0.dist-info/entry_points.txt
ci_package_tools-1.0.0.dist-info/RECORD
