Metadata-Version: 2.4
Name: ci-package-tools
Version: 1.0.0
Summary: A utiliy to package CI artifacts
Author-email: floris vernieuwe <floris@vernieuwe.eu>
Requires-Python: >=3.10
Requires-Dist: click>=8.1.8
